canopy/__init__.py
canopy/chat_engine/__init__.py
canopy/chat_engine/chat_engine.py
canopy/chat_engine/exceptions.py
canopy/chat_engine/history_pruner/__init__.py
canopy/chat_engine/history_pruner/base.py
canopy/chat_engine/history_pruner/raising.py
canopy/chat_engine/history_pruner/recent.py
canopy/chat_engine/query_generator/__init__.py
canopy/chat_engine/query_generator/base.py
canopy/chat_engine/query_generator/cohere.py
canopy/chat_engine/query_generator/function_calling.py
canopy/chat_engine/query_generator/instruction.py
canopy/chat_engine/query_generator/last_message.py
canopy/config_templates/anyscale.yaml
canopy/config_templates/azure.yaml
canopy/config_templates/cohere.yaml
canopy/config_templates/default.yaml
canopy/config_templates/octoai.yaml
canopy/context_engine/__init__.py
canopy/context_engine/context_builder/__init__.py
canopy/context_engine/context_builder/base.py
canopy/context_engine/context_builder/stuffing.py
canopy/context_engine/context_engine.py
canopy/knowledge_base/__init__.py
canopy/knowledge_base/base.py
canopy/knowledge_base/chunker/__init__.py
canopy/knowledge_base/chunker/base.py
canopy/knowledge_base/chunker/langchain_text_splitter.py
canopy/knowledge_base/chunker/markdown.py
canopy/knowledge_base/chunker/recursive_character.py
canopy/knowledge_base/chunker/token_chunker.py
canopy/knowledge_base/knowledge_base.py
canopy/knowledge_base/models.py
canopy/knowledge_base/qdrant/constants.py
canopy/knowledge_base/qdrant/converter.py
canopy/knowledge_base/qdrant/qdrant_knowledge_base.py
canopy/knowledge_base/qdrant/utils.py
canopy/knowledge_base/record_encoder/__init__.py
canopy/knowledge_base/record_encoder/anyscale.py
canopy/knowledge_base/record_encoder/azure_openai.py
canopy/knowledge_base/record_encoder/base.py
canopy/knowledge_base/record_encoder/cohere.py
canopy/knowledge_base/record_encoder/dense.py
canopy/knowledge_base/record_encoder/hybrid.py
canopy/knowledge_base/record_encoder/jina.py
canopy_sdk-0.9.0.dist-info/entry_points.txt
canopy_sdk-0.9.0.dist-info/METADATA
canopy_sdk-0.9.0.dist-info/WHEEL
canopy_sdk-0.9.0.dist-info/LICENSE
canopy_sdk-0.9.0.dist-info/RECORD
