Metadata-Version: 2.1
Name: canopy-sdk
Version: 0.9.0
Summary: Retrieval Augmented Generation (RAG) framework and context engine powered by Pinecone
License: Apache-2.0
Author: Relevance Team
Author-email: relevance@pinecone.io
Requires-Python: >=3.9,<3.13
Classifier: License :: OSI Approved :: Apache Software License
Classifier: Programming Language :: Python :: 3
Classifier: Programming Language :: Python :: 3.9
Classifier: Programming Language :: Python :: 3.10
Classifier: Programming Language :: Python :: 3.11
Provides-Extra: cohere
Provides-Extra: grpc
Provides-Extra: qdrant
Provides-Extra: torch
Provides-Extra: transformers
Requires-Dist: cohere (>=4.37,<5.0) ; extra == "cohere"
Requires-Dist: fastapi (>=0.93.0,<1.0.0)
Requires-Dist: googleapis-common-protos (>=1.53.0) ; extra == "grpc"
Requires-Dist: grpc-gateway-protoc-gen-openapiv2 (==0.1.0) ; extra == "grpc"
Requires-Dist: grpcio (>=1.44.0) ; extra == "grpc"
Requires-Dist: gunicorn (>=21.2.0,<22.0.0)
Requires-Dist: jsonschema (>=4.2.0,<5.0.0)
Requires-Dist: lz4 (>=3.1.3) ; extra == "grpc"
Requires-Dist: openai (>=1.2.3,<2.0.0)
Requires-Dist: pandas (==2.0.0)
Requires-Dist: pandas-stubs (>=2.0.3.230814,<3.0.0.0)
Requires-Dist: pinecone-client (>=3.0.0,<4.0.0)
Requires-Dist: pinecone-text (>=0.8.0,<0.9.0)
Requires-Dist: prompt-toolkit (>=3.0.39,<4.0.0)
Requires-Dist: protobuf (>=3.20.0,<3.21.0) ; extra == "grpc"
Requires-Dist: pyarrow (>=14.0.1,<15.0.0)
Requires-Dist: pydantic (>=2.0.0,<3.0.0)
Requires-Dist: python-dotenv (>=1.0.0,<2.0.0)
Requires-Dist: qdrant-client (>=1.8.0,<2.0.0) ; extra == "qdrant"
Requires-Dist: sentence-transformers (>=2.0.0) ; extra == "torch"
Requires-Dist: sentencepiece (>=0.1.99,<0.2.0)
Requires-Dist: sse-starlette (>=1.6.5,<2.0.0)
Requires-Dist: tenacity (>=8.2.1,<9.0.0)
Requires-Dist: tiktoken (>=0.3.3,<0.4.0)
Requires-Dist: tokenizers (>=0.15.0,<0.16.0)
Requires-Dist: torch (>=1.13.1) ; extra == "torch"
Requires-Dist: tqdm (>=4.66.1,<5.0.0)
Requires-Dist: transformers (>=4.35.2,<5.0.0) ; extra == "transformers"
Requires-Dist: types-jsonschema (>=4.2.0,<5.0.0)
Requires-Dist: types-pyyaml (>=6.0.12.12,<7.0.0.0)
Requires-Dist: types-tqdm (>=4.61.0,<5.0.0)
Requires-Dist: uvicorn (>=0.20.0,<1.0.0)
